Workbook

Sheet Vlookup IF Error
A1: Customer ID | B1: Customer Name | C1: Sales | D1: Quantity | E1: Discount | F1: Profit | N1: Customer ID | O1: Customer Name | P1: Sales | Q1: Quantity | R1: Discount | S1: Profit
A2: CG-12520 | B2: Claire Gute | C2: 261.96 | D2: 2 | E2: 0 | F2: 41.9136 | N2: CG-12520
A3: DV-13045 | B3: Darrin Van Huff | C3: 731.94 | D3: 3 | E3: 0 | F3: 219.582 | N3: CG-12521
A4: SO-20335 | B4: Sean O'Donnell | C4: 14.62 | D4: 2 | E4: 0 | F4: 6.8714
A5: BH-11710 | B5: Brosina Hoffman | C5: 957.5775 | D5: 5 | E5: 0.45 | F5: -383.031
A6: AA-10480 | B6: Andrew Allen | C6: 22.368 | D6: 2 | E6: 0.2 | F6: 2.5164
A7: IM-15070 | B7: Irene Maddox | C7: 48.86 | D7: 7 | E7: 0 | F7: 14.1694

Sheet Nested V Lookup
A1: Order ID | B1: Customer ID | H1: Customer ID | I1: Category | J1: Sub Category | K1: Sales | L1: Profit
A2: CA-2016-152156 | B2: CG-12520 | H2: CG-12520 | I2: Furniture | J2: Bookcases | K2: 261.96 | L2: 41.9136
A3: CA-2016-138688 | B3: DV-13045 | H3: DV-13045 | I3: Furniture | J3: Chairs | K3: 731.94 | L3: 219.582
A4: US-2015-108966 | B4: SO-20335 | H4: SO-20335 | I4: Office Supplies | J4: Labels | K4: 14.62 | L4: 6.8714
A5: CA-2014-115812 | B5: BH-11710 | H5: BH-11710 | I5: Furniture | J5: Tables | K5: 957.5775 | L5: -383.031
A6: CA-2017-114412 | B6: AA-10480 | H6: AA-10480 | I6: Office Supplies | J6: Storage | K6: 22.368 | L6: 2.5164
A7: CA-2016-161389 | B7: IM-15070 | H7: IM-15070 | I7: Furniture | J7: Furnishings | K7: 48.86 | L7: 14.1694
A8: US-2015-118983 | B8: HP-14815 | H8: HP-14815 | I8: Office Supplies | J8: Art | K8: 7.28 | L8: 1.9656
A9: CA-2014-105893 | B9: PK-19075 | H9: PK-19075 | I9: Technology | J9: Phones | K9: 907.152 | L9: 90.7152
A10: CA-2014-167164 | B10: AG-10270 | H10: AG-10270 | I10: Office Supplies | J10: Binders | K10: 18.504 | L10: 5.7825 | O10: =MATCH(H10,H1:H14,0) -> 10
A11: CA-2014-143336 | B11: ZD-21925 | H11: ZD-21925 | I11: Office Supplies | J11: Appliances | K11: 114.9 | L11: 34.47
A12: CA-2016-137330 | B12: KB-16585 | H12: KB-16585 | I12: Furniture | J12: Tables | K12: 1706.184 | L12: 85.3092
A13: US-2017-156909 | B13: SF-20065 | H13: SF-20065 | I13: Technology | J13: Phones | K13: 911.424 | L13: 68.3568
A14: CA-2015-106320 | B14: EB-13870 | H14: EB-13870 | I14: Office Supplies | J14: Paper | K14: 15.552 | L14: 5.4432
A15: CA-2016-121755 | B15: EH-13945 | H15: EH-13945 | I15: Office Supplies | J15: Binders | K15: 407.976 | L15: 132.5922
A16: US-2015-150630 | B16: TB-21520
A17: CA-2017-107727 | B17: MA-17560
A18: CA-2016-117590 | B18: GH-14485 | H18: Order ID | I18: Category | J18: Sub Category | K18: Sales | L18: Profit
A19: CA-2015-117415 | B19: SN-20710 | H19: CA-2016-152156
A20: CA-2017-120999 | B20: LC-16930
A21: CA-2016-101343 | B21: RA-19885
A22: CA-2017-139619 | B22: ES-14080
A23: CA-2016-118255 | B23: ON-18715
A24: CA-2014-146703 | B24: PO-18865
A25: CA-2016-169194 | B25: LH-16900
A26: CA-2015-115742 | B26: DP-13000
A27: CA-2016-105816 | B27: JM-15265
A28: CA-2016-111682 | B28: TB-21055

Sheet Multiple Table Vlookup
A1: Bill No. | B1: Product | C1: Quantity | F1: Bill No. | G1: Product | H1: Quantity | L1: Bill No. | M1: Product | N1: Quantity
A2: 101 | B2: Table | C2: 35 | F2: 111 | G2: Table | H2: 32 | L2: 121 | M2: Table | N2: 95
A3: 102 | B3: Chair | C3: 37 | F3: 112 | G3: Chair | H3: 10 | L3: 122 | M3: Chair | N3: 100
A4: 103 | B4: Pillow | C4: 35 | F4: 113 | G4: Pillow | H4: 27 | L4: 123 | M4: Pillow | N4: 93
A5: 104 | B5: Table | C5: 36 | F5: 114 | G5: Table | H5: 26 | L5: 124 | M5: Table | N5: 96
A6: 105 | B6: Chair | C6: 36 | F6: 115 | G6: Chair | H6: 29 | L6: 125 | M6: Chair | N6: 98
A7: 106 | B7: Pillow | C7: 38 | F7: 116 | G7: Pillow | H7: 33 | L7: 126 | M7: Pillow | N7: 97
A8: 107 | B8: Table | C8: 34 | F8: 117 | G8: Table | H8: 20 | L8: 127 | M8: Table | N8: 91
A9: 108 | B9: Chair | C9: 27 | F9: 118 | G9: Chair | H9: 38 | L9: 128 | M9: Chair | N9: 92
A10: 109 | B10: Pillow | C10: 33 | F10: 119 | G10: Pillow | H10: 40 | L10: 129 | M10: Pillow | N10: 90
A11: 110 | B11: Table | C11: 29 | F11: 120 | G11: Table | H11: 27 | L11: 130 | M11: Table | N11: 99
I14: Bill No. | J14: 110
I15: Product
I16: Quantity

Sheet Vlookup on Multiple Sheet
A1: Customer ID | B1: Sales | C1: Profit | I1: Sales | J1: Profit | K1: Customer ID
A2: CG-12520 | B2: =VLOOKUP($A2,'S-1'!$A$1:$B$15,2,0) -> 261.96 | C2: =VLOOKUP($A2,'S-2'!$A$1:$B$15,2,0) -> 41.9136 | I2: =VLOOKUP($K2,$A$1:$C$15,2,0) -> 261.96 | K2: CG-12520
A3: DV-13045 | B3: =VLOOKUP($A3,'S-1'!$A$1:$B$15,2,0) -> 731.94 | C3: =VLOOKUP($A3,'S-2'!$A$1:$B$15,2,0) -> 219.582 | I3: =VLOOKUP($K3,$A$1:$C$15,2,0) -> 731.94 | K3: DV-13045
A4: SO-20335 | B4: =VLOOKUP($A4,'S-1'!$A$1:$B$15,2,0) -> 14.62 | C4: =VLOOKUP($A4,'S-2'!$A$1:$B$15,2,0) -> 6.8714 | I4: =VLOOKUP($K4,$A$1:$C$15,2,0) -> 14.62 | K4: SO-20335
A5: BH-11710 | B5: =VLOOKUP($A5,'S-1'!$A$1:$B$15,2,0) -> 957.5775 | C5: =VLOOKUP($A5,'S-2'!$A$1:$B$15,2,0) -> -383.031 | I5: =VLOOKUP($K5,$A$1:$C$15,2,0) -> 957.5775 | K5: BH-11710
A6: AA-10480 | B6: =VLOOKUP($A6,'S-1'!$A$1:$B$15,2,0) -> 22.368 | C6: =VLOOKUP($A6,'S-2'!$A$1:$B$15,2,0) -> 2.5164 | I6: =VLOOKUP($K6,$A$1:$C$15,2,0) -> 22.368 | K6: AA-10480
A7: IM-15070 | B7: =VLOOKUP($A7,'S-1'!$A$1:$B$15,2,0) -> 48.86 | C7: =VLOOKUP($A7,'S-2'!$A$1:$B$15,2,0) -> 14.1694 | I7: =VLOOKUP($K7,$A$1:$C$15,2,0) -> 48.86 | K7: IM-15070
A8: HP-14815 | B8: =VLOOKUP($A8,'S-1'!$A$1:$B$15,2,0) -> 7.28 | C8: =VLOOKUP($A8,'S-2'!$A$1:$B$15,2,0) -> 1.9656 | I8: =VLOOKUP($K8,$A$1:$C$15,2,0) -> 7.28 | K8: HP-14815
A9: PK-19075 | B9: =VLOOKUP($A9,'S-1'!$A$1:$B$15,2,0) -> 907.152 | C9: =VLOOKUP($A9,'S-2'!$A$1:$B$15,2,0) -> 90.7152 | I9: =VLOOKUP($K9,$A$1:$C$15,2,0) -> 907.152 | K9: PK-19075
A10: AG-10270 | B10: =VLOOKUP($A10,'S-1'!$A$1:$B$15,2,0) -> 18.504 | C10: =VLOOKUP($A10,'S-2'!$A$1:$B$15,2,0) -> 5.7825 | I10: =VLOOKUP($K10,$A$1:$C$15,2,0) -> 18.504 | K10: AG-10270
A11: ZD-21925 | B11: =VLOOKUP($A11,'S-1'!$A$1:$B$15,2,0) -> 114.9 | C11: =VLOOKUP($A11,'S-2'!$A$1:$B$15,2,0) -> 34.47 | I11: =VLOOKUP($K11,$A$1:$C$15,2,0) -> 114.9 | K11: ZD-21925
A12: KB-16585 | B12: =VLOOKUP($A12,'S-1'!$A$1:$B$15,2,0) -> 1706.184 | C12: =VLOOKUP($A12,'S-2'!$A$1:$B$15,2,0) -> 85.3092 | I12: =VLOOKUP($K12,$A$1:$C$15,2,0) -> 1706.184 | K12: KB-16585
A13: SF-20065 | B13: =VLOOKUP($A13,'S-1'!$A$1:$B$15,2,0) -> 911.424 | C13: =VLOOKUP($A13,'S-2'!$A$1:$B$15,2,0) -> 68.3568 | I13: =VLOOKUP($K13,$A$1:$C$15,2,0) -> 911.424 | K13: SF-20065
... A15: EH-13945 | B15: =VLOOKUP($A15,'S-1'!$A$1:$B$15,2,0) -> 407.976 | C15: =VLOOKUP($A15,'S-2'!$A$1:$B$15,2,0) -> 132.5922 | I15: =VLOOKUP($K15,$A$1:$C$15,2,0) -> 407.976 | K15: EH-13945
I20: Customer ID | J20: Sales | K20: Profit
A21: Sales | B21: Profit | C21: Customer ID | I21: CG-12520 | J21: =INDEX(A21:A35,MATCH(I21,C21:C35,0)) -> 0
A22: =VLOOKUP($A22,'S-1'!$A$1:$B$15,2,0) -> 261.96 | B22: =VLOOKUP($A22,'S-2'!$A$1:$B$15,2,0) -> 41.9136 | C22: CG-12520 | I22: DV-13045
A23: =VLOOKUP($A23,'S-1'!$A$1:$B$15,2,0) -> 731.94 | B23: =VLOOKUP($A23,'S-2'!$A$1:$B$15,2,0) -> 219.582 | C23: DV-13045 | I23: SO-20335
A24: =VLOOKUP($A24,'S-1'!$A$1:$B$15,2,0) -> 14.62 | B24: =VLOOKUP($A24,'S-2'!$A$1:$B$15,2,0) -> 6.8714 | C24: SO-20335 | I24: BH-11710
A25: =VLOOKUP($A25,'S-1'!$A$1:$B$15,2,0) -> 957.5775 | B25: =VLOOKUP($A25,'S-2'!$A$1:$B$15,2,0) -> -383.031 | C25: BH-11710 | I25: AA-10480
A26: =VLOOKUP($A26,'S-1'!$A$1:$B$15,2,0) -> 22.368 | B26: =VLOOKUP($A26,'S-2'!$A$1:$B$15,2,0) -> 2.5164 | C26: AA-10480 | I26: IM-15070
A27: =VLOOKUP($A27,'S-1'!$A$1:$B$15,2,0) -> 48.86 | B27: =VLOOKUP($A27,'S-2'!$A$1:$B$15,2,0) -> 14.1694 | C27: IM-15070 | I27: HP-14815
A28: =VLOOKUP($A28,'S-1'!$A$1:$B$15,2,0) -> 7.28 | B28: =VLOOKUP($A28,'S-2'!$A$1:$B$15,2,0) -> 1.9656 | C28: HP-14815 | I28: PK-19075
A29: =VLOOKUP($A29,'S-1'!$A$1:$B$15,2,0) -> 907.152 | B29: =VLOOKUP($A29,'S-2'!$A$1:$B$15,2,0) -> 90.7152 | C29: PK-19075 | I29: AG-10270
A30: =VLOOKUP($A30,'S-1'!$A$1:$B$15,2,0) -> 18.504 | B30: =VLOOKUP($A30,'S-2'!$A$1:$B$15,2,0) -> 5.7825 | C30: AG-10270 | I30: ZD-21925
A31: =VLOOKUP($A31,'S-1'!$A$1:$B$15,2,0) -> 114.9 | B31: =VLOOKUP($A31,'S-2'!$A$1:$B$15,2,0) -> 34.47 | C31: ZD-21925 | I31: KB-16585
A32: =VLOOKUP($A32,'S-1'!$A$1:$B$15,2,0) -> 1706.184 | B32: =VLOOKUP($A32,'S-2'!$A$1:$B$15,2,0) -> 85.3092 | C32: KB-16585 | I32: SF-20065
A33: =VLOOKUP($A33,'S-1'!$A$1:$B$15,2,0) -> 911.424 | B33: =VLOOKUP($A33,'S-2'!$A$1:$B$15,2,0) -> 68.3568 | C33: SF-20065 | I33: EB-13870
A34: =VLOOKUP($A34,'S-1'!$A$1:$B$15,2,0) -> 15.552 | B34: =VLOOKUP($A34,'S-2'!$A$1:$B$15,2,0) -> 5.4432 | C34: EB-13870 | I34: EH-13945
A35: =VLOOKUP($A35,'S-1'!$A$1:$B$15,2,0) -> 407.976 | B35: =VLOOKUP($A35,'S-2'!$A$1:$B$15,2,0) -> 132.5922 | C35: EH-13945

Sheet S-1
A1: Customer ID | B1: Sales
A2: CG-12520 | B2: 261.96
A3: DV-13045 | B3: 731.94
A4: SO-20335 | B4: 14.62
A5: BH-11710 | B5: 957.5775
A6: AA-10480 | B6: 22.368
A7: IM-15070 | B7: 48.86
A8: HP-14815 | B8: 7.28
A9: PK-19075 | B9: 907.152
A10: AG-10270 | B10: 18.504
A11: ZD-21925 | B11: 114.9
A12: KB-16585 | B12: 1706.184
A13: SF-20065 | B13: 911.424
... A15: EH-13945 | B15: 407.976

Sheet S-2
A1: Customer ID | B1: Profit
A2: CG-12520 | B2: 41.9136
A3: DV-13045 | B3: 219.582
A4: SO-20335 | B4: 6.8714
A5: BH-11710 | B5: -383.031
A6: AA-10480 | B6: 2.5164
A7: IM-15070 | B7: 14.1694
A8: HP-14815 | B8: 1.9656
A9: PK-19075 | B9: 90.7152
A10: AG-10270 | B10: 5.7825
A11: ZD-21925 | B11: 34.47
A12: KB-16585 | B12: 85.3092
A13: SF-20065 | B13: 68.3568
... A15: EH-13945 | B15: 132.5922

Sheet Vlookup- Choose
A1: Customer Name | B1: Sales | C1: Quantity | D1: Discount | E1: Quantity | F1: Customer ID | J1: Customer ID | K1: Quantity | L1: Discount | M1: Customer Name | N1: Sales
A2: Claire Gute | B2: 261.96 | C2: 2 | D2: 0 | E2: 41.9136 | F2: CG-12520 | J2: DV-13045 | K2: =VLOOKUP($J2,CHOOSE({1,2,3,4,5},$F$1:$F$7,$C$1:$C$7,$D$1:$D$7,$A$1:$A$7,$B$1:$B$7),2,0) -> 3 | L2: =VLOOKUP($J2,CHOOSE({1,2,3,4,5},$F$1:$F$7,$C$1:$C$7,$D$1:$D$7,$A$1:$A$7,$B$1:$B$7),3,0) -> 0 | M2: =VLOOKUP($J2,CHOOSE({1,2,3,4,5},$F$1:$F$7,$C$1:$C$7,$D$1:$D$7,$A$1:$A$7,$B$1:$B$7),4,0) -> Darrin Van Huff | N2: =VLOOKUP($J2,CHOOSE({1,2,3,4,5},$F$1:$F$7,$C$1:$C$7,$D$1:$D$7,$A$1:$A$7,$B$1:$B$7),5,0) -> 731.94
A3: Darrin Van Huff | B3: 731.94 | C3: 3 | D3: 0 | E3: 219.582 | F3: DV-13045 | J3: SO-20335 | K3: =VLOOKUP($J3,CHOOSE({1,2,3,4,5},$F$1:$F$7,$C$1:$C$7,$D$1:$D$7,$A$1:$A$7,$B$1:$B$7),2,0) -> 2 | L3: =VLOOKUP($J3,CHOOSE({1,2,3,4,5},$F$1:$F$7,$C$1:$C$7,$D$1:$D$7,$A$1:$A$7,$B$1:$B$7),3,0) -> 0 | M3: =VLOOKUP($J3,CHOOSE({1,2,3,4,5},$F$1:$F$7,$C$1:$C$7,$D$1:$D$7,$A$1:$A$7,$B$1:$B$7),4,0) -> Sean O'Donnell | N3: =VLOOKUP($J3,CHOOSE({1,2,3,4,5},$F$1:$F$7,$C$1:$C$7,$D$1:$D$7,$A$1:$A$7,$B$1:$B$7),5,0) -> 14.62
A4: Sean O'Donnell | B4: 14.62 | C4: 2 | D4: 0 | E4: 6.8714 | F4: SO-20335 | J4: BH-11710 | K4: =VLOOKUP($J4,CHOOSE({1,2,3,4,5},$F$1:$F$7,$C$1:$C$7,$D$1:$D$7,$A$1:$A$7,$B$1:$B$7),2,0) -> 5 | L4: =VLOOKUP($J4,CHOOSE({1,2,3,4,5},$F$1:$F$7,$C$1:$C$7,$D$1:$D$7,$A$1:$A$7,$B$1:$B$7),3,0) -> 0.45 | M4: =VLOOKUP($J4,CHOOSE({1,2,3,4,5},$F$1:$F$7,$C$1:$C$7,$D$1:$D$7,$A$1:$A$7,$B$1:$B$7),4,0) -> Brosina Hoffman | N4: =VLOOKUP($J4,CHOOSE({1,2,3,4,5},$F$1:$F$7,$C$1:$C$7,$D$1:$D$7,$A$1:$A$7,$B$1:$B$7),5,0) -> 957.5775
A5: Brosina Hoffman | B5: 957.5775 | C5: 5 | D5: 0.45 | E5: -383.031 | F5: BH-11710
A6: Andrew Allen | B6: 22.368 | C6: 2 | D6: 0.2 | E6: 2.5164 | F6: AA-10480
A7: Irene Maddox | B7: 48.86 | C7: 7 | D7: 0 | E7: 14.1694 | F7: IM-15070

Sheet Vlookup -Index Match
A1: Customer Name | B1: Sales | C1: Quantity | D1: Discount | E1: Profit | F1: Customer ID | K1: Customer ID | L1: Quantity | M1: Discount | N1: Customer Name | O1: Sales
A2: Claire Gute | B2: 261.96 | C2: 2 | D2: 0 | E2: 41.9136 | F2: CG-12520 | K2: CG-12520 | L2: =INDEX($A$1:$F$7,MATCH($K2,$F$1:$F$7,0),MATCH(L$1,$A$1:$F$1,0)) -> 2 | M2: =INDEX($A$1:$F$7,MATCH($K2,$F$1:$F$7,0),MATCH(M$1,$A$1:$F$1,0)) -> 0 | N2: =INDEX($A$1:$F$7,MATCH($K2,$F$1:$F$7,0),MATCH(N$1,$A$1:$F$1,0)) -> Claire Gute | O2: =INDEX($A$1:$F$7,MATCH($K2,$F$1:$F$7,0),MATCH(O$1,$A$1:$F$1,0)) -> 261.96
A3: Darrin Van Huff | B3: 731.94 | C3: 3 | D3: 0 | E3: 219.582 | F3: DV-13045 | K3: DV-13045 | L3: =INDEX($A$1:$F$7,MATCH($K3,$F$1:$F$7,0),MATCH(L$1,$A$1:$F$1,0)) -> 3 | M3: =INDEX($A$1:$F$7,MATCH($K3,$F$1:$F$7,0),MATCH(M$1,$A$1:$F$1,0)) -> 0 | N3: =INDEX($A$1:$F$7,MATCH($K3,$F$1:$F$7,0),MATCH(N$1,$A$1:$F$1,0)) -> Darrin Van Huff | O3: =INDEX($A$1:$F$7,MATCH($K3,$F$1:$F$7,0),MATCH(O$1,$A$1:$F$1,0)) -> 731.94
A4: Sean O'Donnell | B4: 14.62 | C4: 2 | D4: 0 | E4: 6.8714 | F4: SO-20335 | K4: SO-20335 | L4: =INDEX($A$1:$F$7,MATCH($K4,$F$1:$F$7,0),MATCH(L$1,$A$1:$F$1,0)) -> 2 | M4: =INDEX($A$1:$F$7,MATCH($K4,$F$1:$F$7,0),MATCH(M$1,$A$1:$F$1,0)) -> 0 | N4: =INDEX($A$1:$F$7,MATCH($K4,$F$1:$F$7,0),MATCH(N$1,$A$1:$F$1,0)) -> Sean O'Donnell | O4: =INDEX($A$1:$F$7,MATCH($K4,$F$1:$F$7,0),MATCH(O$1,$A$1:$F$1,0)) -> 14.62
A5: Brosina Hoffman | B5: 957.5775 | C5: 5 | D5: 0.45 | E5: -383.031 | F5: BH-11710 | K5: BH-11710 | L5: =INDEX($A$1:$F$7,MATCH($K5,$F$1:$F$7,0),MATCH(L$1,$A$1:$F$1,0)) -> 5 | M5: =INDEX($A$1:$F$7,MATCH($K5,$F$1:$F$7,0),MATCH(M$1,$A$1:$F$1,0)) -> 0.45 | N5: =INDEX($A$1:$F$7,MATCH($K5,$F$1:$F$7,0),MATCH(N$1,$A$1:$F$1,0)) -> Brosina Hoffman | O5: =INDEX($A$1:$F$7,MATCH($K5,$F$1:$F$7,0),MATCH(O$1,$A$1:$F$1,0)) -> 957.5775
A6: Andrew Allen | B6: 22.368 | C6: 2 | D6: 0.2 | E6: 2.5164 | F6: AA-10480
A7: Irene Maddox | B7: 48.86 | C7: 7 | D7: 0 | E7: 14.1694 | F7: IM-15070
K9: Customer ID | L9: Quantity | M9: Discount | N9: Customer Name | O9: Sales
K10: IM-15070 | L10: =INDEX($A$1:$F$7,MATCH($K10,$F$1:$F$7,0),MATCH(L$9,$A$1:$F$1,0)) -> 7 | M10: =INDEX($A$1:$F$7,MATCH($K10,$F$1:$F$7,0),MATCH(M$9,$A$1:$F$1,0)) -> 0 | N10: =INDEX($A$1:$F$7,MATCH($K10,$F$1:$F$7,0),MATCH(N$9,$A$1:$F$1,0)) -> Irene Maddox | O10: =INDEX($A$1:$F$7,MATCH($K10,$F$1:$F$7,0),MATCH(O$9,$A$1:$F$1,0)) -> 48.86
K11: CG-12520 | L11: =INDEX($A$1:$F$7,MATCH($K11,$F$1:$F$7,0),MATCH(L$9,$A$1:$F$1,0)) -> 2 | M11: =INDEX($A$1:$F$7,MATCH($K11,$F$1:$F$7,0),MATCH(M$9,$A$1:$F$1,0)) -> 0 | N11: =INDEX($A$1:$F$7,MATCH($K11,$F$1:$F$7,0),MATCH(N$9,$A$1:$F$1,0)) -> Claire Gute | O11: =INDEX($A$1:$F$7,MATCH($K11,$F$1:$F$7,0),MATCH(O$9,$A$1:$F$1,0)) -> 261.96
